pytest_synodic-0.1.1.dev6.dist-info/METADATA
pytest_synodic-0.1.1.dev6.dist-info/WHEEL
pytest_synodic-0.1.1.dev6.dist-info/licenses/LICENSE.md
pytest_synodic/__init__.py
pytest_synodic/plugin.py
pytest_synodic/py.typed
pytest_synodic-0.1.1.dev6.dist-info/RECORD
